{
  "update_time": "2026-07-19 21:48",
  "data_date": "2026-07-20",
  "gcp_score": -0.08,
  "pci_score": 1.34,
  "pci_z_score": -0.55,
  "spy_price": 748.79,
  "details": [
    {
      "code": "P_TWD",
      "name": "台幣/地緣",
      "value": 1.3,
      "status": "tight"
    },
    {
      "code": "P_METAL",
      "name": "貴金屬/黃金",
      "value": 0.9,
      "status": "neutral"
    },
    {
      "code": "P_JPY",
      "name": "日圓套息",
      "value": -0.84,
      "status": "neutral"
    },
    {
      "code": "P_EUR",
      "name": "歐元區",
      "value": -0.76,
      "status": "neutral"
    },
    {
      "code": "P_AUD",
      "name": "澳幣/原物料",
      "value": -0.58,
      "status": "neutral"
    },
    {
      "code": "P_CNH",
      "name": "中國/人民幣",
      "value": -0.49,
      "status": "neutral"
    },
    {
      "code": "P_CRYPTO",
      "name": "加密貨幣",
      "value": 0.49,
      "status": "neutral"
    },
    {
      "code": "P_USD",
      "name": "美元池壓力",
      "value": 0.46,
      "status": "neutral"
    },
    {
      "code": "P_KRW",
      "name": "韓元/風險",
      "value": -0.3,
      "status": "neutral"
    },
    {
      "code": "P_EM",
      "name": "新興市場",
      "value": -0.09,
      "status": "neutral"
    }
  ]
}