{
    "last_updated": "2026-05-31 11:16:01",
    "market_data": {
        "jp_10y": 2.661,
        "us_3m": 0.0,
        "jp_3m": 0.0,
        "sofr": 3.62,
        "iorb": 3.65,
        "sofr_date": "2026-05-28"
    },
    "risk_indicators": {
        "high_yield_oas": 0.0,
        "baa_spread": 1.57,
        "financial_stress": -0.76,
        "srf_usage": 0.0,
        "srf_date": "2026-05-29"
    },
    "z_score": {
        "value": 1.9,
        "mean": 1.3738,
        "std": 0.2518,
        "status": "Warning",
        "details": {
            "w5000": 75654.0,
            "m2": 22804.5,
            "ratio": 1.8513
        },
        "history_debug": [
            "S:75654 | M2:22804",
            "R:1.8513 (Mean:1.37)"
        ]
    },
    "client_side_params": {
        "market_vuln": {
            "m2_supply": 22804.5,
            "jgb_10y": 2.661,
            "hist_mean": 1.3738074954062134,
            "hist_std": 0.25181779149809386
        },
        "vol_stress": {
            "hv_mean": 7.9618,
            "hv_std": 2.8511,
            "slope_mean": -0.0409,
            "slope_std": 1.2639,
            "yesterday_hv": 1.9253
        },
        "spread_history_150d": [
            {
                "date": "2025-10-23",
                "spread": 1.33
            },
            {
                "date": "2025-10-24",
                "spread": 1.336
            },
            {
                "date": "2025-10-27",
                "spread": 1.336
            },
            {
                "date": "2025-10-28",
                "spread": 1.322
            },
            {
                "date": "2025-10-29",
                "spread": 1.397
            },
            {
                "date": "2025-10-30",
                "spread": 1.432
            },
            {
                "date": "2025-10-31",
                "spread": 1.44
            },
            {
                "date": "2025-11-03",
                "spread": 1.445
            },
            {
                "date": "2025-11-04",
                "spread": 1.428
            },
            {
                "date": "2025-11-05",
                "spread": 1.496
            },
            {
                "date": "2025-11-06",
                "spread": 1.432
            },
            {
                "date": "2025-11-07",
                "spread": 1.432
            },
            {
                "date": "2025-11-10",
                "spread": 1.449
            },
            {
                "date": "2025-11-11",
                "spread": 1.459
            },
            {
                "date": "2025-11-12",
                "spread": 1.404
            },
            {
                "date": "2025-11-13",
                "spread": 1.451
            },
            {
                "date": "2025-11-14",
                "spread": 1.487
            },
            {
                "date": "2025-11-17",
                "spread": 1.472
            },
            {
                "date": "2025-11-18",
                "spread": 1.462
            },
            {
                "date": "2025-11-19",
                "spread": 1.472
            },
            {
                "date": "2025-11-20",
                "spread": 1.445
            },
            {
                "date": "2025-11-21",
                "spread": 1.402
            },
            {
                "date": "2025-11-24",
                "spread": 1.377
            },
            {
                "date": "2025-11-25",
                "spread": 1.341
            },
            {
                "date": "2025-11-26",
                "spread": 1.337
            },
            {
                "date": "2025-11-28",
                "spread": 1.356
            },
            {
                "date": "2025-12-01",
                "spread": 1.435
            },
            {
                "date": "2025-12-02",
                "spread": 1.425
            },
            {
                "date": "2025-12-03",
                "spread": 1.396
            },
            {
                "date": "2025-12-04",
                "spread": 1.447
            },
            {
                "date": "2025-12-05",
                "spread": 1.478
            },
            {
                "date": "2025-12-08",
                "spread": 1.511
            },
            {
                "date": "2025-12-09",
                "spread": 1.525
            },
            {
                "date": "2025-12-10",
                "spread": 1.503
            },
            {
                "date": "2025-12-11",
                "spread": 1.48
            },
            {
                "date": "2025-12-12",
                "spread": 1.533
            },
            {
                "date": "2025-12-15",
                "spread": 1.521
            },
            {
                "date": "2025-12-16",
                "spread": 1.488
            },
            {
                "date": "2025-12-17",
                "spread": 1.49
            },
            {
                "date": "2025-12-18",
                "spread": 1.455
            },
            {
                "date": "2025-12-19",
                "spread": 1.49
            },
            {
                "date": "2025-12-22",
                "spread": 1.508
            },
            {
                "date": "2025-12-23",
                "spread": 1.508
            },
            {
                "date": "2025-12-24",
                "spread": 1.475
            },
            {
                "date": "2025-12-26",
                "spread": 1.475
            },
            {
                "date": "2025-12-29",
                "spread": 1.455
            },
            {
                "date": "2025-12-30",
                "spread": 1.469
            },
            {
                "date": "2025-12-31",
                "spread": 1.502
            },
            {
                "date": "2026-01-02",
                "spread": 1.526
            },
            {
                "date": "2026-01-05",
                "spread": 1.504
            },
            {
                "date": "2026-01-06",
                "spread": 1.518
            },
            {
                "date": "2026-01-07",
                "spread": 1.477
            },
            {
                "date": "2026-01-08",
                "spread": 1.522
            },
            {
                "date": "2026-01-09",
                "spread": 1.51
            },
            {
                "date": "2026-01-12",
                "spread": 1.526
            },
            {
                "date": "2026-01-13",
                "spread": 1.51
            },
            {
                "date": "2026-01-14",
                "spread": 1.479
            },
            {
                "date": "2026-01-15",
                "spread": 1.499
            },
            {
                "date": "2026-01-16",
                "spread": 1.57
            },
            {
                "date": "2026-01-20",
                "spread": 1.634
            },
            {
                "date": "2026-01-21",
                "spread": 1.592
            },
            {
                "date": "2026-01-22",
                "spread": 1.588
            },
            {
                "date": "2026-01-23",
                "spread": 1.578
            },
            {
                "date": "2026-01-26",
                "spread": 1.552
            },
            {
                "date": "2026-01-27",
                "spread": 1.562
            },
            {
                "date": "2026-01-28",
                "spread": 1.59
            },
            {
                "date": "2026-01-29",
                "spread": 1.566
            },
            {
                "date": "2026-01-30",
                "spread": 1.58
            },
            {
                "date": "2026-02-02",
                "spread": 1.614
            },
            {
                "date": "2026-02-03",
                "spread": 1.613
            },
            {
                "date": "2026-02-04",
                "spread": 1.614
            },
            {
                "date": "2026-02-05",
                "spread": 1.549
            },
            {
                "date": "2026-02-06",
                "spread": 1.545
            },
            {
                "date": "2026-02-09",
                "spread": 1.537
            },
            {
                "date": "2026-02-10",
                "spread": 1.486
            },
            {
                "date": "2026-02-11",
                "spread": 1.511
            },
            {
                "date": "2026-02-12",
                "spread": 1.443
            },
            {
                "date": "2026-02-13",
                "spread": 1.395
            },
            {
                "date": "2026-02-17",
                "spread": 1.391
            },
            {
                "date": "2026-02-18",
                "spread": 1.418
            },
            {
                "date": "2026-02-19",
                "spread": 1.414
            },
            {
                "date": "2026-02-20",
                "spread": 1.425
            },
            {
                "date": "2026-02-23",
                "spread": 1.368
            },
            {
                "date": "2026-02-24",
                "spread": 1.372
            },
            {
                "date": "2026-02-25",
                "spread": 1.387
            },
            {
                "date": "2026-02-26",
                "spread": 1.356
            },
            {
                "date": "2026-02-27",
                "spread": 1.301
            },
            {
                "date": "2026-03-02",
                "spread": 1.387
            },
            {
                "date": "2026-03-03",
                "spread": 1.395
            },
            {
                "date": "2026-03-04",
                "spread": 1.419
            },
            {
                "date": "2026-03-05",
                "spread": 1.485
            },
            {
                "date": "2026-03-06",
                "spread": 1.472
            },
            {
                "date": "2026-03-09",
                "spread": 1.475
            },
            {
                "date": "2026-03-10",
                "spread": 1.475
            },
            {
                "date": "2026-03-11",
                "spread": 1.547
            },
            {
                "date": "2026-03-12",
                "spread": 1.612
            },
            {
                "date": "2026-03-13",
                "spread": 1.624
            },
            {
                "date": "2026-03-16",
                "spread": 1.559
            },
            {
                "date": "2026-03-17",
                "spread": 1.541
            },
            {
                "date": "2026-03-18",
                "spread": 1.598
            },
            {
                "date": "2026-03-19",
                "spread": 1.62
            },
            {
                "date": "2026-03-20",
                "spread": 1.73
            },
            {
                "date": "2026-03-23",
                "spread": 1.673
            },
            {
                "date": "2026-03-24",
                "spread": 1.731
            },
            {
                "date": "2026-03-25",
                "spread": 1.667
            },
            {
                "date": "2026-03-26",
                "spread": 1.755
            },
            {
                "date": "2026-03-27",
                "spread": 1.779
            },
            {
                "date": "2026-03-30",
                "spread": 1.681
            },
            {
                "date": "2026-03-31",
                "spread": 1.65
            },
            {
                "date": "2026-04-01",
                "spread": 1.658
            },
            {
                "date": "2026-04-02",
                "spread": 1.652
            },
            {
                "date": "2026-04-06",
                "spread": 1.674
            },
            {
                "date": "2026-04-07",
                "spread": 1.682
            },
            {
                "date": "2026-04-08",
                "spread": 1.63
            },
            {
                "date": "2026-04-09",
                "spread": 1.632
            },
            {
                "date": "2026-04-10",
                "spread": 1.656
            },
            {
                "date": "2026-04-13",
                "spread": 1.636
            },
            {
                "date": "2026-04-14",
                "spread": 1.595
            },
            {
                "date": "2026-04-15",
                "spread": 1.621
            },
            {
                "date": "2026-04-16",
                "spread": 1.648
            },
            {
                "date": "2026-04-17",
                "spread": 1.585
            },
            {
                "date": "2026-04-20",
                "spread": 1.589
            },
            {
                "date": "2026-04-21",
                "spread": 1.631
            },
            {
                "date": "2026-04-22",
                "spread": 1.633
            },
            {
                "date": "2026-04-23",
                "spread": 1.662
            },
            {
                "date": "2026-04-24",
                "spread": 1.649
            },
            {
                "date": "2026-04-27",
                "spread": 1.675
            },
            {
                "date": "2026-04-28",
                "spread": 1.693
            },
            {
                "date": "2026-04-29",
                "spread": 1.757
            },
            {
                "date": "2026-04-30",
                "spread": 1.729
            },
            {
                "date": "2026-05-01",
                "spread": 1.717
            },
            {
                "date": "2026-05-04",
                "spread": 1.785
            },
            {
                "date": "2026-05-05",
                "spread": 1.755
            },
            {
                "date": "2026-05-06",
                "spread": 1.695
            },
            {
                "date": "2026-05-07",
                "spread": 1.731
            },
            {
                "date": "2026-05-08",
                "spread": 1.703
            },
            {
                "date": "2026-05-11",
                "spread": 1.749
            },
            {
                "date": "2026-05-12",
                "spread": 1.802
            },
            {
                "date": "2026-05-13",
                "spread": 1.82
            },
            {
                "date": "2026-05-14",
                "spread": 1.8
            },
            {
                "date": "2026-05-15",
                "spread": 1.934
            },
            {
                "date": "2026-05-18",
                "spread": 1.962
            },
            {
                "date": "2026-05-19",
                "spread": 2.006
            },
            {
                "date": "2026-05-20",
                "spread": 1.911
            },
            {
                "date": "2026-05-21",
                "spread": 1.925
            },
            {
                "date": "2026-05-22",
                "spread": 1.897
            },
            {
                "date": "2026-05-26",
                "spread": 1.832
            },
            {
                "date": "2026-05-27",
                "spread": 1.82
            },
            {
                "date": "2026-05-28",
                "spread": 1.794
            },
            {
                "date": "2026-05-29",
                "spread": 1.792
            }
        ],
        "gray_rhino_ingredients": {
            "pvd": 1.2,
            "vpd": -0.3,
            "csd": -2.5,
            "lf": -0.77,
            "ttd_slope": -0.0354
        },
        "stlfsi_z_params": {
            "current": 0,
            "mean": 0,
            "std": 1
        },
        "move_z_params": {
            "current": 70.22,
            "mean": 79.67,
            "std": 12.19
        }
    }
}